docsdb/__init__.py
docsdb/export.py
docsdb/main.py
docsdb/mongodb.py
docsdb/serve.py
docsdb/include/__init__.py
docsdb/include/index.html
docsdb/utils/__init__.py
docsdb/utils/docs.py
docsdb/utils/system.py
docsdb/utils/yaml_utils.py
docsdb-0.1.7.dist-info/METADATA
docsdb-0.1.7.dist-info/WHEEL
docsdb-0.1.7.dist-info/entry_points.txt
docsdb-0.1.7.dist-info/top_level.txt
docsdb-0.1.7.dist-info/RECORD
