Metadata-Version: 2.1
Name: docsdb
Version: 0.1.7
Summary: docsdb - generate static documentation for your database
Author: deji
Author-email: deji.a.ibrahim@gmail.com
License: MIT
Requires-Dist: click <=8.1.7,>=8.0.4
Requires-Dist: pymongo <5.0,>=4.3.3
Requires-Dist: PyYAML <=6.0.1,>=5.3
